Workbook

Sheet Demonstr. Financ.
A1: BALANÇO PATRIMONIAL (31/12) | F1: DEMONSTRAÇÃO DO RESULTADO
A2: ATIVO (Bens e direitos) | C2: PASSIVO (Obrigações) | F2: DO EXERCÍCIO
A3: Circulante | B3: =+B4+B6+B7 -> 0 | C3: Circulante | D3: =SUM(D4:D7) -> 0 | F3: Receitas
A4: Caixa e bancos | C4: Fornecedores | F4: ( - ) Imposto sobre venda
C5: Pessoal a pagar | F5: Receita Operacional Líquida | G5: =+G3+G4 -> 0
A6: Contas a receber | C6: Empréstimos | F6: ( - ) Custo do material
A7: Estoques | C7: Imposto a pagar | F7: ( - ) Custo de mão de obra
C8: Não circulante | D8: =+D9 -> 0 | F8: ( - ) Despesa administrativa
A9: Não circulante | B9: =+B10+B11 -> 0 | C9: Passivos longo prazo | F9: Margem operacional | G9: =G5+SUM(G6:G8) -> 0
A10: Equipamentos | C10: PATRIMÔNIO LÍQUIDO | F10: ( - ) Despesa financeira
A11: Imóveis | C11: Capital
C12: Lucros acumulados
A14: TOTAL ATIVO | B14: =+B3+B9 -> 0 | C14: TOTAL PASSIVO + PL | D14: =+D3+D8+D11+D12 -> 0 | F14: Lucro | G14: =+G9+G10 -> 0

Sheet Fluxos
A1: BALANÇO PATRIMONIAL (31/12) | F1: DEMONSTRAÇÃO DO RESULTADO
A2: ATIVO (Bens e direitos) | C2: PASSIVO (Obrigações) | F2: DO EXERCÍCIO
A3: Circulante | B3: =+B4+B6+B7 -> 0 | C3: Circulante | D3: =SUM(D4:D7) -> 0 | F3: Receitas
A4: Caixa e bancos | C4: Fornecedores | F4: ( - ) Imposto sobre venda
C5: Pessoal a pagar | F5: Receita Operacional Líquida | G5: =+G3+G4 -> 0
A6: Contas a receber | C6: Empréstimos | F6: ( - ) Custo do material
A7: Estoques | C7: Imposto a pagar | F7: ( - ) Custo de mão de obra
C8: Não circulante | D8: =+D9 -> 0 | F8: ( - ) Despesa administrativa
A9: Não circulante | B9: =+B10+B11 -> 0 | C9: Passivos longo prazo | F9: Margem operacional | G9: =G5+SUM(G6:G8) -> 0
A10: Equipamentos | C10: PATRIMÔNIO LÍQUIDO | F10: ( - ) Despesa financeira
A11: Imóveis | C11: Capital
C12: Lucros acumulados
A14: TOTAL ATIVO | B14: =+B3+B9 -> 0 | C14: TOTAL PASSIVO + PL | D14: =+D3+D8+D11+D12 -> 0 | F14: Lucro | G14: =+G9+G10 -> 0

Sheet Balanço e resultado - Aula
A1: BALANÇO PATRIMONIAL (31/12) | F1: DEMONSTRAÇÃO DO RESULTADO
A2: ATIVO (Bens e direitos) | C2: PASSIVO (Obrigações) | F2: DO EXERCÍCIO | J2: FATOS CONTÁBEIS
A3: Circulante | B3: =+B4+B6+B7 -> 0 | C3: Circulante | D3: =SUM(D4:D7) -> 0 | F3: Receitas (Vendas) | J3: Abertura da empresa R$ 100.000, em cheque
A4: Caixa e bancos | C4: Fornecedores | F4: ( - ) Imposto sobre venda | J4: Compra de equipamento R$ 80.000, em cheque
C5: Pessoal a pagar | F5: Receita Operacional Líquida | G5: =+G3+G4 -> 0 | J5: Compra de estoque R$ 40.000, a prazo
A6: Contas a receber | C6: Empréstimos | F6: ( - ) Custo do material | J6: Empréstimo bancário R$ 40.000, em duas parcelas de R$ 21.000
A7: Estoques | C7: Imposto a pagar | F7: ( - ) Custo de mão de obra | J7: Venda de produto, a prazo, por R$ 40.000, sendo R$ 4.000 o imposto sobre venda
C8: Não circulante | D8: =+D9 -> 0 | F8: ( - ) Despesa administrativa | J8: R$ 20.000 o custo de material e R$ 4.000 o custo de mão de obra
A9: Não circulante | B9: =+B10+B11 -> 0 | C9: Passivos longo prazo | F9: Margem operacional | G9: =G5+SUM(G6:G8) -> 0 | J9: Despesa administrativa de R$ 1.000, em cheque
A10: Equipamentos | C10: PATRIMÔNIO LÍQUIDO | F10: ( - ) Despesa financeira | J10: Pagamento da primeira parcela do empréstimo
A11: Imóveis | C11: Capital | J11: Encerramento (balancete)
A12: ( - ) Depreciação | C12: Lucros acumulados | J12: Equação fundamental da contabilidade
J13: A = P + PL
A14: TOTAL ATIVO | B14: =+B3+B9 -> 0 | C14: TOTAL PASSIVO + PL | D14: =+D3+D8+D11+D12 -> 0 | F14: Lucro | G14: =+G9+G10 -> 0 | J14: A - P = PL

Sheet Indicadores (exercício)
A1: INDICADORES | J1: Interpretações
A2: Liquidez corrente (R$) = AC / PC = | J2: ="(Para cada R$ 1,00 de dívida de curto prazo, a empresa tem "&TEXT(G2,"R$ ##0,##")&")" -> (Para cada R$ 1,00 de dívida de curto prazo, a empresa tem R$ 0,)
A4: Endividamento geral (R$) = Passivo total / Ativo total = | J4: ="(Para cada R$ 1,00 que a empresa tem, R$ "&TEXT(G4,"##0,##")&" são de terceiros)" -> (Para cada R$ 1,00 que a empresa tem, R$ 0, são de terceiros)
A6: Margem operacional (%) = Margem operacional (R$) / Receita Líquida= | J6: (% de margem operacional)
A8: Retorno do Ativo (%) = Lucro Líquido / Ativo total = | J8: (% de retorno do Ativo)
E10: Lucro Líquido | F10: * | G10: Receita Líquida
E11: Receita Líquida | G11: Ativo Total
E13: Margem líquida | F13: * | G13: Giro | H13: = | J13: (% de retorno do investimento)

Sheet Fatos contábeis
D1: RAZONETES | M1: BALANÇO PATRIMONIAL (31/12) | R1: DEMONSTRAÇÃO DO RESULTADO
B2: FATOS CONTÁBEIS | D2: ATIVO | H2: PASSIVO | J2: RESULTADO | M2: ATIVO (Bens e direitos) | O2: PASSIVO (Obrigações) | R2: DO EXERCÍCIO
B3: Abertura da empresa $ 100.000, em dinheiro | M3: Circulante | N3: =+N4+N5+N6+N7 -> 98000 | O3: Circulante | P3: =SUM(P4:P7) -> 68000 | R3: Receitas (Vendas) | S3: 40000
B4: Compra de equipamento $ 80.000, a vista | D4: 100000 | E4: 80000 | F4: 40000 | I4: 40000 | K4: 40000 | M4: Caixa e bancos | N4: =100000-80000+40000-1000-21000 -> 38000 | O4: Fornecedores | P4: 40000 | R4: ( - ) Imposto sobre venda | S4: -4000
B5: Compra de estoque $ 40.000, a prazo. ICMS = 10% | D5: 40000 | E5: 1000 | M5: Contas a receber | N5: 40000 | O5: Pessoal a pagar | P5: 4000 | R5: Receita Operacional Líquida | S5: =+S3+S4 -> 36000
B6: Empréstimo bancário $ 40.000, em duas parcelas de $ 21.000 | E6: 21000 | F6: 36000 | G6: 20000 | I6: 4000 | J6: 4000 | M6: Estoques | N6: =36000-20000 -> 16000 | O6: Empréstimos | P6: =40000-20000 -> 20000 | R6: ( - ) Custo do material | S6: -20000
B7: Venda de produto, a prazo, por $ 40.000, sendo | M7: ICMS retido | N7: 4000 | O7: Impostos a pagar | P7: 4000 | R7: ( - ) Custo de mão de obra | S7: -4000
B8: $ 20.000 o custo de material e | F8: 4000 | H8: 20000 | I8: 40000 | J8: 20000 | O8: Não circulante | P8: =+P9 -> 0 | R8: ( - ) Despesa administrativa | S8: -1000
B9: $ 4.000 o custo de mão de obra | M9: Não circulante | N9: =+N10+N11 -> 80000 | O9: Passivos longo prazo | P9: 0 | R9: Margem operacional | S9: =S5+SUM(S6:S8) -> 11000
B10: Despesa administrativa de R$ 1.000, em dinheiro | F10: 80000 | I10: 4000 | J10: 4000 | M10: Equipamentos | N10: 80000 | O10: PATRIMÔNIO LÍQUIDO | R10: ( - ) Despesa financeira | S10: -1000
B11: Pagamento da primeira parcela do empréstimo | M11: Imóveis | O11: Capital | P11: 100000
B12: Encerramento (balancete) | H12: PATRIMÔNIO LÍQUIDO | J12: 1000 | M12: ( - ) Depreciação Ac. | N12: 0 | O12: Lucros acumulados | P12: 10000
B13: Equação fundamental da contabilidade
B14: A = P + PL A - P = PL | I14: 100000 | M14: TOTAL ATIVO | N14: =+N3+N9 -> 178000 | O14: TOTAL PASSIVO + PL | P14: =+P3+P8+P11+P12 -> 178000 | R14: Lucro | S14: =+S9+S10 -> 10000
B16: Razonete | J16: 1000

Sheet Razonetes
D1: RAZONETES | M1: BALANÇO PATRIMONIAL (31/12) | R1: DEMONSTRAÇÃO DO RESULTADO
B2: FATOS CONTÁBEIS | D2: ATIVO | H2: PASSIVO | J2: RESULTADO | M2: ATIVO (Bens e direitos) | O2: PASSIVO (Obrigações) | R2: DO EXERCÍCIO
B3: Abertura da empresa $ 100.000, em dinheiro | M3: Circulante | N3: =+N4+N5+N6+N7 -> 98000 | O3: Circulante | P3: =SUM(P4:P7) -> 68000 | R3: Receitas (Vendas) | S3: 40000
B4: Compra de equipamento $ 80.000, a vista | D4: 100000 | E4: 80000 | F4: 40000 | I4: 40000 | K4: 40000 | M4: Caixa e bancos | N4: =100000-80000+40000-1000-21000 -> 38000 | O4: Fornecedores | P4: 40000 | R4: ( - ) Imposto sobre venda | S4: -4000
B5: Compra de estoque $ 40.000, a prazo. ICMS = 10% | D5: 40000 | E5: 1000 | M5: Contas a receber | N5: 40000 | O5: Pessoal a pagar | P5: 4000 | R5: Receita Operacional Líquida | S5: =+S3+S4 -> 36000
B6: Empréstimo bancário $ 40.000, em duas parcelas de $ 21.000 | E6: 21000 | F6: 36000 | G6: 20000 | I6: 4000 | J6: 4000 | M6: Estoques | N6: =36000-20000 -> 16000 | O6: Empréstimos | P6: =40000-20000 -> 20000 | R6: ( - ) Custo do material | S6: -20000
B7: Venda de produto, a prazo, por $ 40.000, sendo | M7: ICMS retido | N7: 4000 | O7: Impostos a pagar | P7: 4000 | R7: ( - ) Custo de mão de obra | S7: -4000
B8: $ 20.000 o custo de material e | F8: 4000 | H8: 20000 | I8: 40000 | J8: 20000 | O8: Não circulante | P8: =+P9 -> 0 | R8: ( - ) Despesa administrativa | S8: -1000
B9: $ 4.000 o custo de mão de obra | M9: Não circulante | N9: =+N10+N11 -> 80000 | O9: Passivos longo prazo | P9: 0 | R9: Margem operacional | S9: =S5+SUM(S6:S8) -> 11000
B10: Despesa administrativa de R$ 1.000, em dinheiro | F10: 80000 | I10: 4000 | J10: 4000 | M10: Equipamentos | N10: 80000 | O10: PATRIMÔNIO LÍQUIDO | R10: ( - ) Despesa financeira | S10: -1000
B11: Pagamento da primeira parcela do empréstimo | M11: Imóveis | O11: Capital | P11: 100000
B12: Encerramento (balancete) | H12: PATRIMÔNIO LÍQUIDO | J12: 1000 | M12: ( - ) Depreciação Ac. | N12: 0 | O12: Lucros acumulados | P12: 10000
B13: Equação fundamental da contabilidade
B14: A = P + PL A - P = PL | I14: 100000 | M14: TOTAL ATIVO | N14: =+N3+N9 -> 178000 | O14: TOTAL PASSIVO + PL | P14: =+P3+P8+P11+P12 -> 178000 | R14: Lucro | S14: =+S9+S10 -> 10000
B16: Razonete | J16: 1000

Sheet Balanço e resultado
D1: RAZONETES | M1: BALANÇO PATRIMONIAL (31/12) | R1: DEMONSTRAÇÃO DO RESULTADO
B2: FATOS CONTÁBEIS | D2: ATIVO | H2: PASSIVO | J2: RESULTADO | M2: ATIVO (Bens e direitos) | O2: PASSIVO (Obrigações) | R2: DO EXERCÍCIO
B3: Abertura da empresa $ 100.000, em dinheiro | M3: Circulante | N3: =+N4+N5+N6+N7 -> 98000 | O3: Circulante | P3: =SUM(P4:P7) -> 68000 | R3: Receitas (Vendas) | S3: 40000
B4: Compra de equipamento $ 80.000, a vista | D4: 100000 | E4: 80000 | F4: 40000 | I4: 40000 | K4: 40000 | M4: Caixa e bancos | N4: =100000-80000+40000-1000-21000 -> 38000 | O4: Fornecedores | P4: 40000 | R4: ( - ) Imposto sobre venda | S4: -4000
B5: Compra de estoque $ 40.000, a prazo. ICMS = 10% | D5: 40000 | E5: 1000 | M5: Contas a receber | N5: 40000 | O5: Pessoal a pagar | P5: 4000 | R5: Receita Operacional Líquida | S5: =+S3+S4 -> 36000
B6: Empréstimo bancário $ 40.000, em duas parcelas de $ 21.000 | E6: 21000 | F6: 36000 | G6: 20000 | I6: 4000 | J6: 4000 | M6: Estoques | N6: =36000-20000 -> 16000 | O6: Empréstimos | P6: =40000-20000 -> 20000 | R6: ( - ) Custo do material | S6: -20000
B7: Venda de produto, a prazo, por $ 40.000, sendo | M7: ICMS retido | N7: 4000 | O7: Impostos a pagar | P7: 4000 | R7: ( - ) Custo de mão de obra | S7: -4000
B8: $ 20.000 o custo de material e | F8: 4000 | H8: 20000 | I8: 40000 | J8: 20000 | O8: Não circulante | P8: =+P9 -> 0 | R8: ( - ) Despesa administrativa | S8: -1000
B9: $ 4.000 o custo de mão de obra | M9: Não circulante | N9: =+N10+N11 -> 80000 | O9: Passivos longo prazo | P9: 0 | R9: Margem operacional | S9: =S5+SUM(S6:S8) -> 11000
B10: Despesa administrativa de R$ 1.000, em dinheiro | F10: 80000 | I10: 4000 | J10: 4000 | M10: Equipamentos | N10: 80000 | O10: PATRIMÔNIO LÍQUIDO | R10: ( - ) Despesa financeira | S10: -1000
B11: Pagamento da primeira parcela do empréstimo | M11: Imóveis | O11: Capital | P11: 100000
B12: Encerramento (balancete) | H12: PATRIMÔNIO LÍQUIDO | J12: 1000 | M12: ( - ) Depreciação Ac. | N12: 0 | O12: Lucros acumulados | P12: 10000
B13: Equação fundamental da contabilidade
B14: A = P + PL A - P = PL | I14: 100000 | M14: TOTAL ATIVO | N14: =+N3+N9 -> 178000 | O14: TOTAL PASSIVO + PL | P14: =+P3+P8+P11+P12 -> 178000 | R14: Lucro | S14: =+S9+S10 -> 10000
B16: Razonete | J16: 1000

Sheet Indicadores
A1: INDICADORES | J1: Interpretações
A2: Liquidez corrente (R$) = AC / PC = | G2: ='Fatos contábeis'!N3/'Fatos contábeis'!P3 -> 1.4411765 | J2: ="(Para cada R$ 1,00 de dívida de curto prazo, a empresa tem "&TEXT(G2,"R$ ##0,##")&")" -> (Para cada R$ 1,00 de dívida de curto prazo, a empresa tem R$ 1,44)
A4: Endividamento geral (R$) = Passivo total / Ativo total = | G4: =(+'Fatos contábeis'!P3+'Fatos contábeis'!P8)/'Fatos contábeis'!N14 -> 0.38202247 | J4: ="(Para cada R$ 1,00 que a empresa tem, R$ "&TEXT(G4,"##0,##")&" são de terceiros)" -> (Para cada R$ 1,00 que a empresa tem, R$ 0,38 são de terceiros)
A6: Margem operacional (%) = Resultado operacional / Receitas líquidas= | I6: =+'Fatos contábeis'!S9/'Fatos contábeis'!S5 -> 0.30555556 | J6: (% de margem operacional)
A8: Retorno do Ativo (%) = Lucro Líquido / Ativo total = | I8: =+'Fatos contábeis'!S14/'Fatos contábeis'!N14 -> 0.056179775 | J8: (% de retorno do investimento)
E10: Lucro Líquido | F10: * | G10: Receita Operacional | H10: = | I10: =+'Fatos contábeis'!S14/'Fatos contábeis'!S5*'Fatos contábeis'!S5/'Fatos contábeis'!N14 -> 0.056179775 | J10: (% de retorno do investimento)
E11: Receita Operacional | G11: Ativo Total
E13: Margem líquida | F13: * | G13: Giro | H13: = | I13: =+E14*G14 -> 0.056179775 | J13: (% de retorno do investimento)
E14: =('Fatos contábeis'!S14/'Fatos contábeis'!S5) -> 0.27777778 | G14: ='Fatos contábeis'!S5/'Fatos contábeis'!N14 -> 0.20224719
